todolog/__init__.py
todolog/decorator.py
todolog/parser.py
todolog-0.1.3.dist-info/LICENSE
todolog-0.1.3.dist-info/WHEEL
todolog-0.1.3.dist-info/METADATA
todolog-0.1.3.dist-info/RECORD
