Metadata-Version: 2.1
Name: todolog
Version: 0.1.3
Summary: Actively Manage ToDos!
Keywords: todo,log,todolog
Author-email: qu3vipon <qu3vipon@gmail.com>
Requires-Python: >=3.10
Classifier: License :: OSI Approved :: MIT License
Classifier: Typing :: Typed
Classifier: Programming Language :: Python :: 3.10
Requires-Dist: tomli
Requires-Dist: pytest ; extra == "test"
Project-URL: Home, https://github.com/qu3vipon/todolog
Provides-Extra: test
